{
  "features": {},
  "id": "poem-0876",
  "guid": "463721f6-742b-48d6-9e5c-449fc40d7054",
  "title": "The World May Stand Still; Or, The Importance Of Real Education",
  "description": null,
  "tags": [
    "furkies-purrkies"
  ],
  "date": "2022-07-24T22:53:14.118Z",
  "lastmod": null,
  "weight": 87600,
  "audio": "poetry-0876.mp3",
  "image": "poetry-0876-illustration.jpg",
  "images": null,
  "artwork": [
    "https://unsplash.com/photos/Q4YQ2Gi1t4c"
  ],
  "resources": null,
  "draft": false,
  "chapter": 4
}